odoo/addons/account_cryptocurrency/README.rst
odoo/addons/account_cryptocurrency/__init__.py
odoo/addons/account_cryptocurrency/__manifest__.py
odoo/addons/account_cryptocurrency/data/res_currency_move_sequence.xml
odoo/addons/account_cryptocurrency/models/__init__.py
odoo/addons/account_cryptocurrency/models/account_account.py
odoo/addons/account_cryptocurrency/models/account_bank_statement.py
odoo/addons/account_cryptocurrency/models/account_move.py
odoo/addons/account_cryptocurrency/models/account_payment.py
odoo/addons/account_cryptocurrency/models/res_currency.py
odoo/addons/account_cryptocurrency/models/res_currency_move.py
odoo/addons/account_cryptocurrency/models/res_currency_move_line.py
odoo/addons/account_cryptocurrency/security/account_cryptocurrency_security.xml
odoo/addons/account_cryptocurrency/security/ir.model.access.csv
odoo/addons/account_cryptocurrency/static/description/icon.png
odoo/addons/account_cryptocurrency/tests/__init__.py
odoo/addons/account_cryptocurrency/tests/test_account_cryptocurrency.py
odoo/addons/account_cryptocurrency/views/account_payment_view.xml
odoo/addons/account_cryptocurrency/views/res_currency_move_line_view.xml
odoo/addons/account_cryptocurrency/views/res_currency_move_menuitem.xml
odoo/addons/account_cryptocurrency/views/res_currency_move_view.xml
odoo/addons/account_cryptocurrency/views/res_currency_view.xml
odoo11_addon_account_cryptocurrency-11.0.1.0.0.dist-info/DESCRIPTION.rst
odoo11_addon_account_cryptocurrency-11.0.1.0.0.dist-info/METADATA
odoo11_addon_account_cryptocurrency-11.0.1.0.0.dist-info/RECORD
odoo11_addon_account_cryptocurrency-11.0.1.0.0.dist-info/WHEEL
odoo11_addon_account_cryptocurrency-11.0.1.0.0.dist-info/metadata.json
odoo11_addon_account_cryptocurrency-11.0.1.0.0.dist-info/top_level.txt
